{"pageProps":{"studio":[{"categoria":"Inmunología-serología","id":"te8Z1YYA2wI2mNooXsjR","precio":307,"descripcion":"Mide la proteína producida por las células normales así como por células malignas de la glándula prostática.","procedimiento":"Se realiza mediante una punción venosa, para obtener la muestra sanguínea.","incluido-paquetes":["Check up masculino ","Perfil prostático (marcadores tumorales)"],"nombre":"Ag Prostático Específico (PSA TOTAL)","indicaciones":"Ayuno mínimo de 8 h, máximo 12 h. No haber eyaculado 72 horas antes."}]},"__N_SSG":true}