{"pageProps":{"studio":[{"procedimiento":"Se realiza mediante una punción venosa, para obtener la muestra sanguínea.","indicaciones":"Ayuno mínimo de 8 h, máximo 12 h","nombrePaquete":"","descripcion":"La medición de la cistatina C es útil en la detección precoz de la enfermedad renal, especialmente cuando otras pruebas o parámetros todavía no se alteran y antes incluso de que aparezcan signos y síntomas","id":"hJiHNIhKXSL87nR623hf","nombre":"Cistatina  C ","precio":"956","categoria":"Inmunología-serología"}]},"__N_SSG":true}