{"pageProps":{"studio":[{"precio":50,"categoria":"Química clínica-Bioquímica","descripcion":"El análisis de creatinina es una forma de medir el funcionamiento de los riñones al momento de filtrar los desechos de la sangre. La creatinina es un compuesto químico que resulta de los procesos de producción de energía de los músculos","nombre":"Creatinina","indicaciones":"Ayuno mínimo de 8 h, máximo 12 h","procedimiento":"Se realiza mediante una punción venosa, para obtener la muestra sanguínea.","id":"s7ywBZAeLIrtTTEtWami"}]},"__N_SSG":true}