{"pageProps":{"studio":[{"precio":64,"indicaciones":"Ayuno mínimo de 8 h, máximo 12 h","id":"ABymiqXwkCa6JQus0dPj","categoria":"Química clínica-Bioquímica","descripcion":"Proteína producida por el hígado. La albúmina ingresa al torrente sanguíneo y ayuda a mantener el líquido sin que se filtre de los vasos sanguíneos a otros tejidos. También transporta varias hormonas, vitaminas y enzimas sustancias por el cuerpo.","nombre":"Albúmina","procedimiento":"Se realiza mediante una punción venosa, para obtener la muestra sanguínea."}]},"__N_SSG":true}