{"pageProps":{"studio":[{"procedimiento":"Se entrega la muestra de heces en un frasco limpio y estéril de boca ancha con tapa rosca. Debe ser entregada al laboratorio antes de que cumpla las 2 horas de recolección.","precio":240,"id":"vnvXwtrtt1Pr68ykedbK","descripcion":"Detección de Cryptosporidiasis","indicaciones":"Se debe recolectar en una superficie limpia y seca (no sacar de la taza del baño) y sin contaminarse con orina. Se lleva al laboratorio una muestra representativa de 10g de heces en un frasco limpio y estéril con boca ancha y taparosca. No debe estar con tratamiento antibiótico, ni antidiarreico o antiparasitarios, no utilizar medicamentos en zona perianal ni supositorios. Tomar la muestra antes o después del periodo menstrual.","nombre":"Búsqueda de Cryptosporidium","categoria":"Microbiología"}]},"__N_SSG":true}