{"pageProps":{"studio":[{"indicaciones":"Ayuno mínimo de 8 h, máximo 12 h","descripcion":"La carotenemia o hipercarotenemia es el exceso de caroteno y, aunque no es tóxico ni particularmente peligrosa, puede producir una ligerea coloración amarilla o anaranjada de la piel pero no de la conjuntiva de los ojos, lo que la distingue de la ictericia.","categoria":"Pruebas especiales","procedimiento":"Se realiza mediante una punción venosa, para obtener la muestra sanguínea.","precio":582,"id":"PWMp4XfcMSzx4u1nVGxc","nombre":"Carotenos"}]},"__N_SSG":true}