{"pageProps":{"studio":[{"precio":914,"id":"v1tvLdXpAQdKUalYkLyI","descripcion":"Estudio de sangre que cuantifica las principales hormonas que intervienen en el funcionamiento ovárico y glándula pituitaria. Hormona foliculo estimulante (FSH)\nHormona luteinizante (LH)\nProlactina serica   Testosterona total\nProgesterona serica\nEstradiol","categoria":"Endocrinología (hormonas)","procedimiento":"Se realiza mediante una punción venosa, para obtener la muestra sanguínea.","nombre":"Perfil Ginecológico","indicaciones":"Ayuno mínimo de 8 h, máximo 12 h"}]},"__N_SSG":true}