{"pageProps":{"studio":[{"descripcion":"Mide el nivel de glucagon en sangre post carga a los 120min.","procedimiento":"Se realiza mediante una punción venosa, para obtener la muestra sanguínea. Durante el tiempo que de duración del estudio el paciente  permanecerá en el laboratorio, en reposo y sin actividad física.","precio":346,"nombre":"Glucagón a los 120 min.","indicaciones":"Requiere preescripción médica. Solicite informes de curvas post carga.","id":"Guf6DQT8KMYLXbleo4ry","categoria":"Química clínica-Bioquímica"}]},"__N_SSG":true}