{"pageProps":{"studio":[{"indicaciones":"Ayuno mínimo de 8 h, máximo 12 h","procedimiento":"Se realiza mediante una punción venosa, para obtener la muestra sanguínea.","nombre":"Perfil de lípidos II","descripcion":"Mide las concentraciones de distintos tipos de grasas en la sangre. Lipidos totales\nColesterol\nTrigliceridos\nColesterol HDL\nColesterol LDL\nColesterol VLDL\nElectroforesis de lipoproteinas","id":"roOfIQ4cEdPAiaGTqgcE","precio":580,"categoria":"Química clínica-Bioquímica"}]},"__N_SSG":true}