{"pageProps":{"studio":[{"precio":580,"nombre":"Perfil de lípidos II","procedimiento":"Se realiza mediante una punción venosa, para obtener la muestra sanguínea.","id":"roOfIQ4cEdPAiaGTqgcE","indicaciones":"Ayuno mínimo de 8 h, máximo 12 h","categoria":"Química clínica-Bioquímica","descripcion":"Mide las concentraciones de distintos tipos de grasas en la sangre. Lipidos totales\nColesterol\nTrigliceridos\nColesterol HDL\nColesterol LDL\nColesterol VLDL\nElectroforesis de lipoproteinas"}]},"__N_SSG":true}