{"pageProps":{"studio":[{"categoria":"Química clínica-Bioquímica","indicaciones":"Recolectar chorro medio de una orina al azar que haya permanecido en vejiga 4 horas. No recolectar la primera orina de la mañana ni durante el periodo menstrual. Se recolecta en laboratorio.","id":"TnSv5fPu4q94wpxNOOAR","descripcion":"Prueba que detecta proteínas en orina (proteinuria), es un signo de daño renal.","nombre":"Proteínas en Orina","procedimiento":"Se entrega la muestra de orina al laboratorio, la cual puede usted recolectar en su domicilio o en el laboratorio.","precio":140}]},"__N_SSG":true}